checkticket_api/checkticket_api/__init__.py
checkticket_api/checkticket_api/__main__.py
checkticket_api/checkticket_api/serve.py
contactdb_api/contactdb_api/__init__.py
contactdb_api/contactdb_api/__main__.py
contactdb_api/contactdb_api/serve.py
events_api/events_api/__init__.py
events_api/events_api/__main__.py
events_api/events_api/serve.py
intelmq_fody_backend/__init__.py
intelmq_fody_backend/serve.py
intelmq_fody_backend-0.11.1.data/scripts/fody-adduser
intelmq_fody_backend-0.11.1.dist-info/licenses/agpl-3.0.txt
session/__init__.py
session/config.py
session/files.py
session/session.py
session/setup.py
tickets_api/tickets_api/__init__.py
tickets_api/tickets_api/__main__.py
tickets_api/tickets_api/serve.py
intelmq_fody_backend-0.11.1.dist-info/METADATA
intelmq_fody_backend-0.11.1.dist-info/WHEEL
intelmq_fody_backend-0.11.1.dist-info/top_level.txt
intelmq_fody_backend-0.11.1.dist-info/RECORD
