Metadata-Version: 2.4
Name: intelmq-fody-backend
Version: 0.11.1
Summary:  A backend to serve intelmq-cb-mailgen data for the webapp fody. 
Home-page: https://github.com/Intevation/intelmq-fody-backend
Author: Intevation GmbH
Author-email: info@intevation.de
Maintainer: Intevation GmbH
Maintainer-email: sebastian.wagner@intevation.de
License: AGPLv3
Requires-Python: <3.13
License-File: agpl-3.0.txt
Dynamic: author
Dynamic: author-email
Dynamic: home-page
Dynamic: license
Dynamic: license-file
Dynamic: requires-python
Dynamic: summary
